zope.app.applicationcontrol-4.1.0-py3.9-nspkg.pth
zope/app/applicationcontrol/__init__.py
zope/app/applicationcontrol/applicationcontrol.py
zope/app/applicationcontrol/configure.zcml
zope/app/applicationcontrol/ftesting.zcml
zope/app/applicationcontrol/i18n.py
zope/app/applicationcontrol/interfaces.py
zope/app/applicationcontrol/runtimeinfo.py
zope/app/applicationcontrol/testing.py
zope/app/applicationcontrol/zopeversion.py
zope/app/applicationcontrol/browser/__init__.py
zope/app/applicationcontrol/browser/configure.zcml
zope/app/applicationcontrol/browser/runtimeinfo.pt
zope/app/applicationcontrol/browser/runtimeinfo.py
zope/app/applicationcontrol/browser/servercontrol.pt
zope/app/applicationcontrol/browser/servercontrol.py
zope/app/applicationcontrol/browser/translationdomaincontrol.pt
zope/app/applicationcontrol/browser/translationdomaincontrol.py
zope/app/applicationcontrol/browser/zodbcontrol.pt
zope/app/applicationcontrol/browser/zodbcontrol.py
zope/app/applicationcontrol/browser/tests/__init__.py
zope/app/applicationcontrol/browser/tests/test_errorredirect.py
zope/app/applicationcontrol/browser/tests/test_runtimeinfoview.py
zope/app/applicationcontrol/browser/tests/test_servercontrolview.py
zope/app/applicationcontrol/browser/tests/test_translationdomaincontrol.py
zope/app/applicationcontrol/browser/tests/test_translationdomaincontrol_functional.py
zope/app/applicationcontrol/browser/tests/test_zodbcontrol.py
zope/app/applicationcontrol/browser/tests/zodb.rst
zope/app/applicationcontrol/tests/__init__.py
zope/app/applicationcontrol/tests/test_zopeversion.py
zope/app/applicationcontrol/tests/view_macros.pt
zope.app.applicationcontrol-4.1.0.dist-info/LICENSE.txt
zope.app.applicationcontrol-4.1.0.dist-info/METADATA
zope.app.applicationcontrol-4.1.0.dist-info/WHEEL
zope.app.applicationcontrol-4.1.0.dist-info/namespace_packages.txt
zope.app.applicationcontrol-4.1.0.dist-info/top_level.txt
zope.app.applicationcontrol-4.1.0.dist-info/RECORD
