Metadata-Version: 2.1
Name: zope.app.applicationcontrol
Version: 4.1.0
Summary: Zope application control
Home-page: https://github.com/zopefoundation/zope.app.applicationcontrol
Author: Zope Foundation and Contributors
Author-email: zope-dev@zope.org
License: ZPL 2.1
Keywords: zope3 application control
Platform: UNKNOWN
Classifier: Development Status :: 5 - Production/Stable
Classifier: Environment :: Web Environment
Classifier: Intended Audience :: Developers
Classifier: License :: OSI Approved :: Zope Public License
Classifier: Programming Language :: Python
Classifier: Programming Language :: Python :: 2
Classifier: Programming Language :: Python :: 2.7
Classifier: Programming Language :: Python :: 3
Classifier: Programming Language :: Python :: 3.5
Classifier: Programming Language :: Python :: 3.6
Classifier: Programming Language :: Python :: 3.7
Classifier: Programming Language :: Python :: 3.8
Classifier: Programming Language :: Python :: 3.9
Classifier: Programming Language :: Python :: 3.10
Classifier: Programming Language :: Python :: Implementation :: CPython
Classifier: Programming Language :: Python :: Implementation :: PyPy
Classifier: Natural Language :: English
Classifier: Operating System :: OS Independent
Classifier: Topic :: Internet :: WWW/HTTP
Classifier: Framework :: Zope :: 3
License-File: LICENSE.txt
Requires-Dist: setuptools
Requires-Dist: ZODB
Requires-Dist: zope.applicationcontrol (>=4.0.1)
Requires-Dist: zope.component
Requires-Dist: zope.i18n
Requires-Dist: zope.i18nmessageid
Requires-Dist: zope.interface
Requires-Dist: zope.size
Requires-Dist: zope.traversing (>=3.7.0)
Provides-Extra: test
Requires-Dist: webtest ; extra == 'test'
Requires-Dist: zope.app.appsetup (>=4.0.0) ; extra == 'test'
Requires-Dist: zope.app.authentication (>=4.0.0) ; extra == 'test'
Requires-Dist: zope.app.basicskin (>=4.0.0) ; extra == 'test'
Requires-Dist: zope.app.component (>=4.0.0) ; extra == 'test'
Requires-Dist: zope.app.container (>=4.0.0) ; extra == 'test'
Requires-Dist: zope.app.locales (>=4.0.0) ; extra == 'test'
Requires-Dist: zope.app.pagetemplate (>=4.0.0) ; extra == 'test'
Requires-Dist: zope.app.publication (>=4.2.1) ; extra == 'test'
Requires-Dist: zope.app.wsgi (>=4.1.0) ; extra == 'test'
Requires-Dist: zope.applicationcontrol (>=4.0.1) ; extra == 'test'
Requires-Dist: zope.authentication (>=4.2.1) ; extra == 'test'
Requires-Dist: zope.annotation (>=4.4.1) ; extra == 'test'
Requires-Dist: zope.browser (>=2.1.0) ; extra == 'test'
Requires-Dist: zope.browsermenu (>=4.1.1) ; extra == 'test'
Requires-Dist: zope.browserpage (>=4.1.0) ; extra == 'test'
Requires-Dist: zope.browserresource (>=4.1.0) ; extra == 'test'
Requires-Dist: zope.container (>=4.1.0) ; extra == 'test'
Requires-Dist: zope.formlib (>=4.3.0) ; extra == 'test'
Requires-Dist: zope.i18nmessageid (>=4.1.0) ; extra == 'test'
Requires-Dist: zope.interface (>=4.4.0) ; extra == 'test'
Requires-Dist: zope.login (>=2.0.0) ; extra == 'test'
Requires-Dist: zope.pagetemplate (>=4.2.1) ; extra == 'test'
Requires-Dist: zope.password (>=4.2.0) ; extra == 'test'
Requires-Dist: zope.pluggableauth (>=2.2.0) ; extra == 'test'
Requires-Dist: zope.principalregistry (>=4.0.0) ; extra == 'test'
Requires-Dist: zope.publisher (>=4.3.1) ; extra == 'test'
Requires-Dist: zope.schema (>=4.4.2) ; extra == 'test'
Requires-Dist: zope.securitypolicy (>=4.1.0) ; extra == 'test'
Requires-Dist: zope.session (>=4.1.0) ; extra == 'test'
Requires-Dist: zope.site (>=4.0.0) ; extra == 'test'
Requires-Dist: zope.testbrowser (>=5.2) ; extra == 'test'
Requires-Dist: zope.testing ; extra == 'test'
Requires-Dist: zope.testrunner ; extra == 'test'
